{
	"color": {
		"primary": {
			"50": "#eff6ff",
			"100": "#dbeafe",
			"200": "#bfdbfe",
			"300": "#93c5fd",
			"400": "#60a5fa",
			"500": "#3b82f6",
			"600": "#2563eb",
			"700": "#1d4ed8",
			"800": "#1e40af",
			"900": "#1e3a8a",
			"950": "#172554"
		},
		"secondary": {
			"50": "#f8fafc",
			"100": "#f1f5f9",
			"200": "#e2e8f0",
			"300": "#cbd5e1",
			"400": "#94a3b8",
			"500": "#64748b",
			"600": "#475569",
			"700": "#334155",
			"800": "#1e293b",
			"900": "#0f172a",
			"950": "#020617"
		},
		"accent": {
			"50": "#f0fdfa",
			"100": "#ccfbf1",
			"200": "#99f6e4",
			"300": "#5eead4",
			"400": "#2dd4bf",
			"500": "#14b8a6",
			"600": "#0d9488",
			"700": "#0f766e",
			"800": "#115e59",
			"900": "#134e4a",
			"950": "#042f2e"
		},
		"success": {
			"50": "#ecfdf5",
			"100": "#d1fae5",
			"200": "#a7f3d0",
			"300": "#6ee7b7",
			"400": "#34d399",
			"500": "#10b981",
			"600": "#059669",
			"700": "#047857",
			"800": "#065f46",
			"900": "#064e3b",
			"950": "#022c22"
		},
		"warning": {
			"50": "#fffbeb",
			"100": "#fef3c7",
			"200": "#fde68a",
			"300": "#fcd34d",
			"400": "#fbbf24",
			"500": "#f59e0b",
			"600": "#d97706",
			"700": "#b45309",
			"800": "#92400e",
			"900": "#78350f",
			"950": "#451a03"
		},
		"error": {
			"50": "#fef2f2",
			"100": "#fee2e2",
			"200": "#fecaca",
			"300": "#fca5a5",
			"400": "#f87171",
			"500": "#ef4444",
			"600": "#dc2626",
			"700": "#b91c1c",
			"800": "#991b1b",
			"900": "#7f1d1d",
			"950": "#450a0a"
		},
		"info": {
			"50": "#eff6ff",
			"100": "#dbeafe",
			"200": "#bfdbfe",
			"300": "#93c5fd",
			"400": "#60a5fa",
			"500": "#3b82f6",
			"600": "#2563eb",
			"700": "#1d4ed8",
			"800": "#1e40af",
			"900": "#1e3a8a",
			"950": "#172554"
		},
		"neutral": {
			"50": "#fafafa",
			"100": "#f5f5f5",
			"200": "#e5e5e5",
			"300": "#d4d4d4",
			"400": "#a3a3a3",
			"500": "#737373",
			"600": "#525252",
			"700": "#404040",
			"800": "#262626",
			"900": "#171717",
			"950": "#0a0a0a"
		},
		"surface": {
			"light": {
				"primary": "#ffffff",
				"secondary": "#f8fafc",
				"tertiary": "#f1f5f9",
				"quaternary": "#e2e8f0"
			},
			"dark": {
				"primary": "#0f172a",
				"secondary": "#1e293b",
				"tertiary": "#334155",
				"quaternary": "#475569"
			}
		},
		"text": {
			"light": {
				"primary": "#0f172a",
				"secondary": "#475569",
				"tertiary": "#64748b",
				"disabled": "#94a3b8"
			},
			"dark": {
				"primary": "#f8fafc",
				"secondary": "#cbd5e1",
				"tertiary": "#94a3b8",
				"disabled": "#64748b"
			}
		},
		"border": {
			"light": {
				"primary": "#e2e8f0",
				"secondary": "#cbd5e1",
				"focus": "#3b82f6"
			},
			"dark": {
				"primary": "#334155",
				"secondary": "#475569",
				"focus": "#60a5fa"
			}
		}
	},
	"typography": {
		"fontFamily": {
			"heading": ["Libre Baskerville", "serif"],
			"body": ["Roboto", "sans-serif"],
			"subtitle": ["Noto Serif Variable", "serif"],
			"mono": ["JetBrains Mono", "Consolas", "Monaco", "monospace"]
		},
		"fontSize": {
			"xs": "0.75rem",
			"sm": "0.875rem",
			"base": "1rem",
			"lg": "1.125rem",
			"xl": "1.25rem",
			"2xl": "1.5rem",
			"3xl": "1.875rem",
			"4xl": "2.25rem",
			"5xl": "3rem",
			"6xl": "3.75rem"
		},
		"fontWeight": {
			"light": 300,
			"normal": 400,
			"medium": 500,
			"semibold": 600,
			"bold": 700,
			"extrabold": 800
		},
		"lineHeight": {
			"tight": 1.25,
			"snug": 1.375,
			"normal": 1.5,
			"relaxed": 1.625,
			"loose": 2
		},
		"letterSpacing": {
			"tighter": "-0.05em",
			"tight": "-0.025em",
			"normal": "0em",
			"wide": "0.025em",
			"wider": "0.05em",
			"widest": "0.1em"
		}
	},
	"spacing": {
		"0": "0px",
		"1": "0.25rem",
		"2": "0.5rem",
		"3": "0.75rem",
		"4": "1rem",
		"5": "1.25rem",
		"6": "1.5rem",
		"8": "2rem",
		"10": "2.5rem",
		"12": "3rem",
		"16": "4rem",
		"20": "5rem",
		"24": "6rem",
		"32": "8rem",
		"40": "10rem",
		"48": "12rem",
		"56": "14rem",
		"64": "16rem"
	},
	"borderRadius": {
		"none": "0px",
		"sm": "0.25rem",
		"base": "0.375rem",
		"md": "0.5rem",
		"lg": "0.75rem",
		"xl": "1rem",
		"2xl": "1.5rem",
		"3xl": "1.875rem",
		"full": "9999px"
	},
	"elevation": {
		"none": "none",
		"sm": "0 1px 2px 0 rgb(0 0 0 / 0.05)",
		"base": "0 1px 3px 0 rgb(0 0 0 / 0.1), 0 1px 2px -1px rgb(0 0 0 / 0.1)",
		"md": "0 4px 6px -1px rgb(0 0 0 / 0.1), 0 2px 4px -2px rgb(0 0 0 / 0.1)",
		"lg": "0 10px 15px -3px rgb(0 0 0 / 0.1), 0 4px 6px -4px rgb(0 0 0 / 0.1)",
		"xl": "0 20px 25px -5px rgb(0 0 0 / 0.1), 0 8px 10px -6px rgb(0 0 0 / 0.1)",
		"2xl": "0 25px 50px -12px rgb(0 0 0 / 0.25)",
		"inner": "inset 0 2px 4px 0 rgb(0 0 0 / 0.05)"
	},
	"transition": {
		"duration": {
			"75": "75ms",
			"100": "100ms",
			"150": "150ms",
			"200": "200ms",
			"300": "300ms",
			"500": "500ms",
			"700": "700ms",
			"1000": "1000ms"
		},
		"timing": {
			"linear": "linear",
			"in": "cubic-bezier(0.4, 0, 1, 1)",
			"out": "cubic-bezier(0, 0, 0.2, 1)",
			"inOut": "cubic-bezier(0.4, 0, 0.2, 1)"
		}
	},
	"breakpoints": {
		"xs": "0px",
		"sm": "600px",
		"md": "960px",
		"lg": "1280px",
		"xl": "1920px"
	}
}
